README.rst
setup.py
WxRobot/__init__.py
WxRobot/message.py
WxRobot/reply.py
WxRobot/webwxapi.py
WxRobot/wxrobot.py
wxrobot.egg-info/PKG-INFO
wxrobot.egg-info/SOURCES.txt
wxrobot.egg-info/dependency_links.txt
wxrobot.egg-info/requires.txt
wxrobot.egg-info/top_level.txt
wxrobot.egg-info/zip-safe