Metadata-Version: 1.1
Name: wxrobot
Version: 0.13
Summary: a python wechat robot framework for personal account
Home-page: https://github.com/sharpdeep/WxRobot
Author: sharpdeep
Author-email: cairuishen@gmail.com
License: MIT
Keywords: wechat weixin robot wxrobot
Platform: UNKNOWN
Classifier: License :: OSI Approved :: MIT License
Classifier: Programming Language :: Python :: 3.4
Classifier: Intended Audience :: Developers
Classifier: Operating System :: MacOS
Classifier: Operating System :: POSIX
Classifier: Operating System :: POSIX :: Linux
Classifier: Topic :: Software Development :: Libraries
Classifier: Topic :: Software Development :: Libraries :: Python Modules
Classifier: Topic :: Utilities
